[
    {
    "temperature": 1.456894478539,
    "top_p": 0.802839712270468,
    "top_k": 76,
    "repetition_penalty": 1.078632672846121,
    "no_repeat_ngram_size": 3,
    "num_beams": 4
    },
    {
    "temperature": 0.6559143330117907,
    "top_p": 0.9975892995327533,
    "top_k": 67,
    "repetition_penalty": 1.3420454368466015,
    "no_repeat_ngram_size": 2,
    "num_beams": 3
    },
    {
    "temperature": 0.6929649401132001,
    "top_p": 0.893255154172798,
    "top_k": 73,
    "repetition_penalty": 1.1900061712909855,
    "no_repeat_ngram_size": 3,
    "num_beams": 3
}
]